omobono/__init__.py
omobono/dsl/__init__.py
omobono/dsl/plans.py
omobono/errors.py
omobono/types/__init__.py
omobono/types/arrow_support.py
omobono/types/coupon.py
omobono/types/currency_support.py
omobono/types/discount.py
omobono/types/effective_range.py
omobono/types/factory.py
omobono/types/fee.py
omobono/types/interval.py
omobono/types/omobono_unit_registry.py
omobono/types/option.py
omobono/types/plan.py
omobono/types/plan_cost.py
omobono/types/quantity_support.py
omobono/types/rate_support.py
omobono/types/resource.py
omobono/types/rich_type.py
omobono/types/usage.py
omobono-0.1.0.dist-info/METADATA
omobono-0.1.0.dist-info/WHEEL
omobono-0.1.0.dist-info/RECORD
