Metadata-Version: 2.1
Name: omobono
Version: 0.1.0
Summary: 
Author: Peter Nuernberg
Author-email: peter.nuernberg@wpengine.com
Requires-Python: >=3.11,<4.0
Classifier: Programming Language :: Python :: 3
Classifier: Programming Language :: Python :: 3.11
Requires-Dist: jupyter (>=1.0.0,<2.0.0)
Requires-Dist: pandas (>=2.0.1,<3.0.0)
Requires-Dist: pint (>=0.21,<0.22)
